odoo/addons/pos_partner_birthdate/README.rst
odoo/addons/pos_partner_birthdate/__init__.py
odoo/addons/pos_partner_birthdate/__manifest__.py
odoo/addons/pos_partner_birthdate/i18n/es.po
odoo/addons/pos_partner_birthdate/i18n/fr.po
odoo/addons/pos_partner_birthdate/i18n/it.po
odoo/addons/pos_partner_birthdate/i18n/pos_partner_birthdate.pot
odoo/addons/pos_partner_birthdate/models/__init__.py
odoo/addons/pos_partner_birthdate/models/pos_session.py
odoo/addons/pos_partner_birthdate/readme/CONTRIBUTORS.md
odoo/addons/pos_partner_birthdate/readme/DESCRIPTION.md
odoo/addons/pos_partner_birthdate/readme/newsfragments/.gitkeep
odoo/addons/pos_partner_birthdate/static/description/icon.png
odoo/addons/pos_partner_birthdate/static/description/index.html
odoo/addons/pos_partner_birthdate/static/src/js/ClientDetailsEdit.esm.js
odoo/addons/pos_partner_birthdate/static/src/js/PartnerLine.esm.js
odoo/addons/pos_partner_birthdate/static/src/js/PosDB.esm.js
odoo/addons/pos_partner_birthdate/static/src/xml/screens.xml
odoo_addon_pos_partner_birthdate-17.0.1.1.0.4.dist-info/METADATA
odoo_addon_pos_partner_birthdate-17.0.1.1.0.4.dist-info/WHEEL
odoo_addon_pos_partner_birthdate-17.0.1.1.0.4.dist-info/top_level.txt
odoo_addon_pos_partner_birthdate-17.0.1.1.0.4.dist-info/RECORD
