Metadata-Version: 2.1
Name: odoo-addon-pos_partner_birthdate
Version: 17.0.1.1.0.4
Requires-Python: >=3.10
Requires-Dist: odoo-addon-partner_contact_birthdate>=17.0dev,<17.1dev
Requires-Dist: odoo>=17.0a,<17.1dev
Summary: Adds the birthdate in the customer screen of POS
Home-page: https://github.com/OCA/pos
License: AGPL-3
Author: Emanuel Cino, Odoo Community Association (OCA)
Author-email: support@odoo-community.org
Classifier: Programming Language :: Python
Classifier: Framework :: Odoo
Classifier: Framework :: Odoo :: 17.0
Classifier: License :: OSI Approved :: GNU Affero General Public License v3
Classifier: Development Status :: 4 - Beta
